adev_tools/__init__.py
adev_tools/adev_branch.py
adev_tools/adev_lib.py
adev_tools/ci_copy.py
adev_tools/ci_lib.py
adev_tools/ci_stlink.py
adev_tools/config_example.py
adev_tools/diff2commit.py
adev_tools/gdrive_scope_config.py
adev_tools/gdrive_service_account_upload.py
adev_tools/git_commit.py
adev_tools/gitlab_runner_status.py
adev_tools/issues.py
adev_tools/open_gdrive_altium.py
adev_tools/post-build.py
adev_tools/pre-build.py
adev_tools/py_cloneupstream.py
adev_tools/py_fork.py
adev_tools/py_go.py
adev_tools/test_branch_functionality.py
adev_tools/test_gdrive_connection.py
adev_tools/test_upload_download.py
adev_tools/wip_py_project_status.py
adev_tools-0.1.1.dist-info/licenses/LICENSE
adev_tools-0.1.1.dist-info/METADATA
adev_tools-0.1.1.dist-info/WHEEL
adev_tools-0.1.1.dist-info/entry_points.txt
adev_tools-0.1.1.dist-info/top_level.txt
adev_tools-0.1.1.dist-info/RECORD
