Metadata-Version: 2.4
Name: adev-tools
Version: 0.1.1
Summary: Advanced Development Tools for GitLab, Jira, and CI/CD automation
Author-email: JLTech <dev@jltech.com>
License-Expression: MIT
Project-URL: Homepage, https://github.com/jltech/adev-tools
Project-URL: Documentation, https://github.com/jltech/adev-tools/blob/main/README.md
Project-URL: Repository, https://github.com/jltech/adev-tools.git
Project-URL: Bug Tracker, https://github.com/jltech/adev-tools/issues
Keywords: gitlab,jira,ci-cd,development-tools,automation
Classifier: Development Status :: 4 - Beta
Classifier: Intended Audience :: Developers
Classifier: Operating System :: OS Independent
Classifier: Programming Language :: Python :: 3
Classifier: Programming Language :: Python :: 3.8
Classifier: Programming Language :: Python :: 3.9
Classifier: Programming Language :: Python :: 3.10
Classifier: Programming Language :: Python :: 3.11
Classifier: Topic :: Software Development :: Version Control :: Git
Classifier: Topic :: Software Development :: Bug Tracking
Classifier: Topic :: System :: Systems Administration
Requires-Python: >=3.8
License-File: LICENSE
Requires-Dist: requests>=2.31.0
Requires-Dist: GitPython>=3.1.0
Requires-Dist: jira>=3.4.0
Requires-Dist: python-gitlab>=3.15.0
Requires-Dist: argparse
Requires-Dist: pytz
Requires-Dist: tabulate
Requires-Dist: wcwidth
Requires-Dist: pandas
Requires-Dist: openai
Requires-Dist: ollama
Requires-Dist: PyYAML>=6.0
Provides-Extra: dev
Requires-Dist: pytest>=7.0; extra == "dev"
Requires-Dist: black>=22.0; extra == "dev"
Requires-Dist: flake8>=4.0; extra == "dev"
Requires-Dist: mypy>=0.991; extra == "dev"
Dynamic: license-file
